<?xml version="1.0" encoding="utf-8"?>
<configurable>
  <sku>STBTCNNTD</sku>
  <i18n_name>BOOTCUT IN NEW YORK DARK</i18n_name>
  <i18n_name_de>BOOTCUT IN NEW YORK DARK</i18n_name_de>
  <i18n_name_nl>BOOTCUT IN NEW YORK DARK</i18n_name_nl>
  <i18n_name_fr>BOOTCUT IN NEW YORK DARK</i18n_name_fr>
  <i18n_name_it>BOOTCUT IN NEW YORK DARK</i18n_name_it>
  <i18n_name_es>BOOTCUT IN NEW YORK DARK</i18n_name_es>
  <product_start_date>2011-01-01</product_start_date>
  <product_end_date>2017-05-01</product_end_date>
  <i18n_description>Take your basic Bootcut jean, give it a new elegance with a classic dark wash and authentic yellow stitching, and you have an instant classic. You'll never put a fashion foot wrong with this multifunctional wardrobe winner.</i18n_description>
  <i18n_description_de>&lt;ul&gt;&lt;li&gt;Basic-Bootcut Schnitt&lt;/li&gt;&#13;
&lt;li&gt;klassisch dunkles Denim&lt;/li&gt;&#13;
&lt;li&gt;authentische gelbe Nähte&lt;/li&gt;&#13;
&lt;li&gt;multifunktional&lt;/li&gt;&#13;
&lt;li&gt;Mit dieser Jeans liegen Sie immer richtig&lt;/li&gt;&lt;/ul&gt;</i18n_description_de>
  <i18n_description_nl>Neem je Bootcut basismodel, voeg er een vleugje nieuwe elegantie aan toe met een klassieke donkere wassing en authentieke gele stiksels, en je krijgt een echte klassieker. Je gooit gegarandeerd hoge ogen met deze veelzijdige garderobetopper.</i18n_description_nl>
  <i18n_description_fr>Le Bootcut basique a été revisité pour lui donner une nouvelle élégance avec un lavage foncé et des surpiqûres jaunes. Tous les ingrédients d’un classique. Les fautes de goût sont impossibles avec ce modèle incontournable et polyvalent.</i18n_description_fr>
  <i18n_description_it></i18n_description_it>
  <i18n_description_es>Take your basic Bootcut jean, give it a new elegance with a classic dark wash and authentic yellow stitching, and you have an instant classic. You'll never put a fashion foot wrong with this multifunctional wardrobe winner.</i18n_description_es>
  <i18n_short_description>BOOTCUT IN NEW YORK DARK</i18n_short_description>
  <i18n_short_description_de>BOOTCUT IN NEW YORK DARK</i18n_short_description_de>
  <i18n_short_description_nl>BOOTCUT IN NEW YORK DARK</i18n_short_description_nl>
  <i18n_short_description_fr>BOOTCUT IN NEW YORK DARK</i18n_short_description_fr>
  <i18n_short_description_it>BOOTCUT IN NEW YORK DARK</i18n_short_description_it>
  <i18n_short_description_es>BOOTCUT IN NEW YORK DARK</i18n_short_description_es>
  <i18n_product_details>&lt;ul&gt;&lt;li&gt;A very expensive brand's signature squiggle back pocket&lt;/li&gt;&lt;li&gt;98% cotton 2% elasthan&lt;/li&gt;&lt;li&gt;zip fly&lt;/li&gt;&lt;li&gt;Regular waist&lt;/li&gt;&lt;li&gt;All of our products are made in Europe or USA&lt;/li&gt;&lt;li&gt;Average weight 700 gr.&lt;/li&gt;&lt;/ul&gt;</i18n_product_details>
  <i18n_product_details_de>&lt;ul&gt;&lt;li&gt;Die Signature Squiggle Backpocket von A very expensive brand&lt;/li&gt;&lt;li&gt;98 % Baumwolle 2 % Elastan&lt;/li&gt;&lt;li&gt;Reisverschlussleiste&lt;/li&gt;&lt;li&gt;Regular waist&lt;/li&gt;&lt;li&gt;Unsere Produkte werden in Europa und den USA hergestellt&lt;/li&gt;&lt;li&gt;Durchschnittliches Gewicht 700 gr&lt;/li&gt;&lt;/ul&gt;</i18n_product_details_de>
  <i18n_product_details_nl>&lt;ul&gt;&lt;li&gt;A very expensive brand's signature squiggle back pocket&lt;/li&gt;&lt;li&gt;98% Katoen 2% Elasthane&lt;/li&gt;&lt;li&gt;Ritssluiting&lt;/li&gt;&lt;li&gt;Al onze producten worden gemaakt in Europa of de Verenigde Staten&lt;/li&gt;&lt;/ul&gt;</i18n_product_details_nl>
  <i18n_product_details_fr>&lt;ul&gt;&lt;li&gt;A very expensive brand's squiggle poche&lt;/li&gt;&lt;li&gt;98% Coton 2% Elasthane&lt;/li&gt;&lt;li&gt;Fermeture Zip&lt;/li&gt;&lt;li&gt;Tous nos produits sont fabriqués en Europe ou aux Etats-Unis&lt;/li&gt;&lt;/ul&gt;</i18n_product_details_fr>
  <i18n_product_details_it></i18n_product_details_it>
  <i18n_product_details_es>&lt;ul&gt;&lt;li&gt;98% Algodón 2% Elastán&lt;/li&gt;&lt;li&gt;zip fly&lt;/li&gt;&lt;li&gt;Regular waist&lt;/li&gt;&lt;li&gt;All of our products are made in Europe or USA&lt;/li&gt;&lt;li&gt;Average weight 700 gr.&lt;/li&gt;&lt;/ul&gt;</i18n_product_details_es>
  <i18n_product_moreaboutthefit>The Bootcut is A very expensive brand's original premium jean. It has a natural rise, comfortable hip and thigh and a classic bootcut leg opening. It's offered with our signature squiggle or a variety of back pocket designs.</i18n_product_moreaboutthefit>
  <i18n_product_moreaboutthefit_de>A very expensive brand's original Premium-Jeans. Mit regulärer Leibhöhe, bequemer Hüft- und Schenkelweite und einem klassischen Bootcut. Erhältlich mit unserem "Squiggle"-Logo und verschiedenen anderen Taschendesigns.</i18n_product_moreaboutthefit_de>
  <i18n_product_moreaboutthefit_nl>De Bootcut is de originele topjeans van A very expensive brand. Hij heeft een natuurlijke heuplijn, een comfortabele snit aan heup en dijen en waaiert uit aan de onderpijpen. Op de achterzak werd onze signature squiggle of een van de vele andere designs aangebracht.</i18n_product_moreaboutthefit_nl>
  <i18n_product_moreaboutthefit_fr>Le Bootcut est le premier jean haut de gamme de A very expensive brand. Reposant sur la taille naturelle, confortable au niveau des hanches et des cuisses, il se termine en bas par une coupe semi-évasée classique. Il est proposé avec le logo ou divers motifs brodés sur les poches arrière.</i18n_product_moreaboutthefit_fr>
  <i18n_product_moreaboutthefit_it></i18n_product_moreaboutthefit_it>
  <i18n_product_moreaboutthefit_es>The Bootcut is A very expensive brand's original premium jean. It has a natural rise, comfortable hip and thigh and a classic bootcut leg opening. It's offered with our signature squiggle or a variety of back pocket designs.</i18n_product_moreaboutthefit_es>
  <price>200</price>
  <price_uk>180</price_uk>
  <price_de>200</price_de>
  <price_be>200</price_be>
  <price_nl>200</price_nl>
  <price_fr>200</price_fr>
  <price_it>200</price_it>
  <price_pan_en>200</price_pan_en>
  <price_pan_es>200</price_pan_es>
  <price_pan_fr>200</price_pan_fr>
  <price_pan_de>200</price_pan_de>
  <special_price></special_price>
  <special_from_date></special_from_date>
  <special_to_date></special_to_date>
  <special_price_uk></special_price_uk>
  <special_from_date_uk></special_from_date_uk>
  <special_to_date_uk></special_to_date_uk>
  <special_price_de></special_price_de>
  <special_from_date_de></special_from_date_de>
  <special_to_date_de></special_to_date_de>
  <special_price_nl></special_price_nl>
  <special_from_date_nl></special_from_date_nl>
  <special_to_date_nl></special_to_date_nl>
  <special_price_be></special_price_be>
  <special_from_date_be></special_from_date_be>
  <special_to_date_be></special_to_date_be>
  <special_price_fr></special_price_fr>
  <special_from_date_fr></special_from_date_fr>
  <special_to_date_fr></special_to_date_fr>
  <special_price_it></special_price_it>
  <special_from_date_it></special_from_date_it>
  <special_to_date_it></special_to_date_it>
  <special_price_pan_en></special_price_pan_en>
  <special_from_date_pan_en></special_from_date_pan_en>
  <special_to_date_pan_en></special_to_date_pan_en>
  <special_price_pan_es></special_price_pan_es>
  <special_from_date_pan_es></special_from_date_pan_es>
  <special_to_date_pan_es></special_to_date_pan_es>
  <special_price_pan_fr></special_price_pan_fr>
  <special_from_date_pan_fr></special_from_date_pan_fr>
  <special_to_date_pan_fr></special_to_date_pan_fr>
  <special_price_pan_de></special_price_pan_de>
  <special_from_date_pan_de></special_from_date_pan_de>
  <special_to_date_pan_de></special_to_date_pan_de>
  <news_from_date>2011-01-01</news_from_date>
  <image_front>stbtcnntd_front_2.jpg</image_front>
  <image_back>stbtcnntd_back_2.jpg</image_back>
  <image_pocket>stbtcnntd_pocket_2.jpg</image_pocket>
  <image_wash>STBTCNNTD_wash.jpg</image_wash>
  <small_image></small_image>
  <thumbnail></thumbnail>
  <url_key></url_key>
  <color></color>
  <bubble_new_collection></bubble_new_collection>
  <bubble_sale></bubble_sale>
  <bubble_best_seller></bubble_best_seller>
  <bubble_limited_edition></bubble_limited_edition>
  <gender>Women</gender>
  <fit_group>BOOTCUT</fit_group>
  <fit_code>BOOTCUT</fit_code>
  <wash_group>DARK BLUE</wash_group>
  <enable_special_area>Yes</enable_special_area>
  <special_area_static_block_id>Special_In_Store</special_area_static_block_id>
  <delivery_return_static_block_id>product_tab_delivery_return</delivery_return_static_block_id>
  <status>Disabled</status>
  <visibility>Nowhere</visibility>
  <super_attributes>size</super_attributes>
  <website>base</website>
  <category_ids>7,</category_ids>
  <main_cat_seo></main_cat_seo>
  <details_care></details_care>
</configurable>
